[
  {
    "id": "user-1",
    "name": "Current User",
    "email": "user@rented.tn",
    "avatar": "https://images.unsplash.com/photo-1599566150163-29194dcaad36?w=200&h=200&fit=crop",
    "verificationStatus": "verified",
    "activeMode": "vendor"
  },
  {
    "id": "ahmed",
    "name": "Ahmed Ben Ali",
    "email": "ahmed@rented.tn",
    "avatar": "https://images.unsplash.com/photo-1507003211169-0a1dd7228f2d?w=200&h=200&fit=crop",
    "verificationStatus": "verified",
    "activeMode": "vendor"
  },
  {
    "id": "fatma",
    "name": "Fatma Trabelsi",
    "email": "fatma@rented.tn",
    "avatar": "https://images.unsplash.com/photo-1438761681033-6461ffad8d80?w=200&h=200&fit=crop",
    "verificationStatus": "verified",
    "activeMode": "vendor"
  },
  {
    "id": "karim",
    "name": "Karim Jlassi",
    "email": "karim@rented.tn",
    "avatar": "https://images.unsplash.com/photo-1500648767791-00dcc994a43e?w=200&h=200&fit=crop",
    "verificationStatus": "unverified",
    "activeMode": "buyer"
  },
  {
    "id": "yasmine",
    "name": "Yasmine Mansour",
    "email": "yasmine@rented.tn",
    "avatar": "https://images.unsplash.com/photo-1534528741775-53994a69daeb?w=200&h=200&fit=crop",
    "verificationStatus": "pending_review",
    "activeMode": "buyer"
  },
  {
    "id": "nizar",
    "name": "Nizar Bouzid",
    "email": "nizar@rented.tn",
    "avatar": "https://images.unsplash.com/photo-1531427186611-ecfd6d936c79?w=200&h=200&fit=crop",
    "verificationStatus": "verified",
    "activeMode": "buyer"
  },
  {
    "id": "salma",
    "name": "Salma Turki",
    "email": "salma@rented.tn",
    "avatar": "https://images.unsplash.com/photo-1544005313-94ddf0286df2?w=200&h=200&fit=crop",
    "verificationStatus": "verified",
    "activeMode": "buyer"
  },
  {
    "id": "anis",
    "name": "Anis Chaabane",
    "email": "anis@rented.tn",
    "avatar": "https://images.unsplash.com/photo-1506794778202-cad84cf45f1d?w=200&h=200&fit=crop",
    "verificationStatus": "verified",
    "activeMode": "vendor"
  },
  {
    "id": "rim",
    "name": "Rim Dhaouadi",
    "email": "rim@rented.tn",
    "avatar": "https://images.unsplash.com/photo-1494790108377-be9c29b29330?w=200&h=200&fit=crop",
    "verificationStatus": "verified",
    "activeMode": "buyer"
  },
  {
    "id": "mehdi",
    "name": "Mehdi Khemiri",
    "email": "mehdi@rented.tn",
    "avatar": "https://images.unsplash.com/photo-1522075469751-3a6694fb2f61?w=200&h=200&fit=crop",
    "verificationStatus": "verified",
    "activeMode": "vendor"
  }
]
